youtube_me.py
youtube_me-0.1.data/scripts/youtube_me.py
youtube_me-0.1.dist-info/DESCRIPTION.rst
youtube_me-0.1.dist-info/METADATA
youtube_me-0.1.dist-info/metadata.json
youtube_me-0.1.dist-info/RECORD
youtube_me-0.1.dist-info/top_level.txt
youtube_me-0.1.dist-info/WHEEL
