Metadata-Version: 2.0
Name: youtube-me
Version: 0.1
Summary: Automatic YouTube downloading...
Home-page: UNKNOWN
Author: James Milne
Author-email: jmilne@graphic-designer.com
License: Public Domain
Platform: any
Classifier: Development Status :: 3 - Alpha
Classifier: Environment :: Console
Classifier: License :: Public Domain
Classifier: Operating System :: OS Independent
Classifier: Programming Language :: Python
Requires-Dist: youtube-dl
